gitcher/__init__.py
gitcher/__main__.py
gitcher/completer.py
gitcher/dictionary.py
gitcher/model_layer.py
gitcher/not_found_prof_error.py
gitcher/prof.py
gitcher-3.2.data/data/LICENSE
gitcher-3.2.data/data/share/man/man1/gitcher.1
gitcher-3.2.dist-info/LICENSE
gitcher-3.2.dist-info/METADATA
gitcher-3.2.dist-info/WHEEL
gitcher-3.2.dist-info/entry_points.txt
gitcher-3.2.dist-info/top_level.txt
gitcher-3.2.dist-info/RECORD
